fixedta/__init__.py
fixedta/core.py
fixedta/custom.py
fixedta/candles/__init__.py
fixedta/candles/cdl_doji.py
fixedta/candles/cdl_inside.py
fixedta/candles/cdl_pattern.py
fixedta/candles/cdl_z.py
fixedta/candles/ha.py
fixedta/cycles/__init__.py
fixedta/cycles/ebsw.py
fixedta/momentum/__init__.py
fixedta/momentum/ao.py
fixedta/momentum/apo.py
fixedta/momentum/bias.py
fixedta/momentum/bop.py
fixedta/momentum/brar.py
fixedta/momentum/cci.py
fixedta/momentum/cfo.py
fixedta/momentum/cg.py
fixedta/momentum/cmo.py
fixedta/momentum/coppock.py
fixedta/momentum/cti.py
fixedta/momentum/dm.py
fixedta/momentum/er.py
fixedta/momentum/eri.py
fixedta/momentum/fisher.py
fixedta/momentum/inertia.py
fixedta/momentum/kdj.py
fixedta/momentum/kst.py
fixedta/momentum/macd.py
fixedta/momentum/mom.py
fixedta/momentum/pgo.py
fixedta/momentum/ppo.py
fixedta/momentum/psl.py
fixedta/momentum/pvo.py
fixedta/momentum/qqe.py
fixedta/momentum/roc.py
fixedta/momentum/rsi.py
fixedta/momentum/rsx.py
fixedta/momentum/rvgi.py
fixedta/momentum/slope.py
fixedta/momentum/smi.py
fixedta/momentum/squeeze.py
fixedta/momentum/squeeze_pro.py
fixedta/momentum/stc.py
fixedta/momentum/stoch.py
fixedta/momentum/stochrsi.py
fixedta/momentum/td_seq.py
fixedta/momentum/trix.py
fixedta/momentum/tsi.py
fixedta/momentum/uo.py
fixedta/momentum/willr.py
fixedta/overlap/__init__.py
fixedta/overlap/alma.py
fixedta/overlap/dema.py
fixedta/overlap/ema.py
fixedta/overlap/fwma.py
fixedta/overlap/hilo.py
fixedta/overlap/hl2.py
fixedta/overlap/hlc3.py
fixedta/overlap/hma.py
fixedta/overlap/hwma.py
fixedta/overlap/ichimoku.py
fixedta/overlap/jma.py
fixedta/overlap/kama.py
fixedta/overlap/linreg.py
fixedta/overlap/ma.py
fixedta/overlap/mcgd.py
fixedta/overlap/midpoint.py
fixedta/overlap/midprice.py
fixedta/overlap/ohlc4.py
fixedta/overlap/pwma.py
fixedta/overlap/rma.py
fixedta/overlap/sinwma.py
fixedta/overlap/sma.py
fixedta/overlap/ssf.py
fixedta/overlap/supertrend.py
fixedta/overlap/swma.py
fixedta/overlap/t3.py
fixedta-0.0.6.dist-info/METADATA
fixedta-0.0.6.dist-info/WHEEL
fixedta-0.0.6.dist-info/top_level.txt
fixedta-0.0.6.dist-info/RECORD
